{
    "id": "ru_RU_devilsadvocate",
    "name": "Адвокат дьявола",
    "team": "minion",
    "firstNight": 22.0,
    "firstNightReminder": [
      { "text": "Пробудите " },
      { "text": "Адвоката дьявола", "color": "red" },
      { "text": ". Он указывают на любого игрока. Усыпите " },
      { "text": "Адвоката Дьявола", "color": "red" },
      { "text": ". Поставьте пометку " },
      { "text": "«Переживает казнь»", "color": "magenta" },
      { "text": " рядом с жетоном роли выбранного игрока." }
    ],
    "otherNight": 13.0,
    "otherNightReminder": [
      { "text": "Уберите пометку " },
      { "text": "«Переживает казнь»", "color": "magenta" },
      { "text": " из игры, если еще не сделали этого. Пробудите " },
      { "text": "Адвоката дьявола", "color": "red" },
      { "text": ". Он указывают на любого игрока " },
      { "text": "(не того же, что в прошлую ночь)", "italic": true },
      { "text": ". Усыпите " },
      { "text": "Адвоката Дьявола", "color": "red" },
      { "text": ". Поставьте пометку " },
      { "text": "«Переживает казнь»", "color": "magenta" },
      { "text": " рядом с жетоном роли выбранного игрока." }
    ],
    "reminders": ["Переживает казнь"],
    "setup": false,
    "ability": [
      { "text": "Каждую ночь", "bold": true },
      { "text": ": выберите " },
      { "text": "живого", "bold": true },
      { "text": " игрока " },
      { "text": "(не того же, что в прошлую ночь)", "italic": true },
      { "text": ". Если на следующий день его " },
      { "text": "казнят", "bold": true },
      { "text": ", он не умирает." }
    ],
    "image": "https://botc.1nv.is/wiki/images/5/5d/Devilsadvocate.png"
}